mxs/__init__.py
mxs/__version__.py
mxs/api/__init__.py
mxs/api/pattern.py
mxs/cli/__init__.py
mxs/cli/error.py
mxs/cli/solvers.py
mxs/web/__init__.py
mxs/web/pattern.py
mxs/web/static/style.css
mxs/web/templates/base.html
mxs/web/templates/pattern/answer.html
mxs/web/templates/pattern/pv.html
mxs-0.0.2.dist-info/LICENSE
mxs-0.0.2.dist-info/METADATA
mxs-0.0.2.dist-info/WHEEL
mxs-0.0.2.dist-info/entry_points.txt
mxs-0.0.2.dist-info/top_level.txt
mxs-0.0.2.dist-info/RECORD
