Metadata-Version: 2.1
Name: mxs
Version: 0.0.2
Summary: UNKNOWN
License: AGPLv3
Platform: UNKNOWN
License-File: LICENSE
Requires-Dist: flask
